saiyaku/__init__.py
saiyaku/api.py
saiyaku/compat.py
saiyaku-2023.12.11.dist-info/LICENSE
saiyaku-2023.12.11.dist-info/METADATA
saiyaku-2023.12.11.dist-info/WHEEL
saiyaku-2023.12.11.dist-info/RECORD
