Metadata-Version: 2.1
Name: saiyaku
Version: 2023.12.11
Summary: Auto-Retry Decorator for Python
Home-page: https://github.com/animemoeus/saiyaku
License: Apache-2.0
Keywords: saiyaku,retry,decorator,auto-retry,animemoeus
Author: Arter Tendean
Author-email: arter.tendean.07@gmail.com
Requires-Python: >=3.8,<4.0
Classifier: License :: OSI Approved :: Apache Software License
Classifier: Programming Language :: Python :: 3
Classifier: Programming Language :: Python :: 3.8
Classifier: Programming Language :: Python :: 3.9
Classifier: Programming Language :: Python :: 3.10
Classifier: Programming Language :: Python :: 3.11
Classifier: Programming Language :: Python :: 3.12
Project-URL: Documentation, https://github.com/animemoeus/saiyaku#saiyaku-auto-retry-decorator-for-python
Project-URL: Repository, https://github.com/animemoeus/saiyaku
